setup.py
smtpsinkd.py
smtpsink.egg-info/PKG-INFO
smtpsink.egg-info/SOURCES.txt
smtpsink.egg-info/dependency_links.txt
smtpsink.egg-info/requires.txt
smtpsink.egg-info/top_level.txt