Metadata-Version: 1.0
Name: smtpsink
Version: 0.0.1
Summary: An SMTP Sink with a Web UI.
Home-page: http://github.com/lyda/smtpsink
Author: Kevin Lyda
Author-email: kevin@ie.suberic.net
License: GPLv3
Keywords: smtp mail sink fake development test testing
Platform: UNKNOWN
